bark_ml-0.4.32.dist-info/RECORD
bark_ml-0.4.32.dist-info/LICENSE
bark_ml-0.4.32.dist-info/METADATA
bark_ml-0.4.32.dist-info/top_level.txt
bark_ml-0.4.32.dist-info/WHEEL
bark_ml/__init__.py
bark_ml/core.so
bark_ml/pip_package.py
bark_ml/evaluators/__init__.py
bark_ml/evaluators/general_evaluator.py
bark_ml/evaluators/evaluator_configs.py
bark_ml/experiment/__init__.py
bark_ml/experiment/experiment.py
bark_ml/experiment/py_experiment_tests.py
bark_ml/experiment/experiment_runner.py
bark_ml/commons/__init__.py
bark_ml/commons/tracer.py
bark_ml/commons/py_spaces.py
bark_ml/commons/debug_settings.py
bark_ml/tests/__init__.py
bark_ml/tests/py_apollo_tests.py
bark_ml/tests/py_behavior_tests.py
bark_ml/tests/py_observer_tests.py
bark_ml/tests/py_library_tfa_tests.py
bark_ml/tests/py_bark_behavior_model_tests.py
bark_ml/tests/py_library_torch_agents_tests.py
bark_ml/tests/py_graph_nets_tests.py
bark_ml/tests/py_environment_tests.py
bark_ml/tests/py_evaluator_tests.py
bark_ml/tests/py_graph_observer_tests.py
bark_ml/library_wrappers/__init__.py
bark_ml/library_wrappers/lib_tf_agents/__init__.py
bark_ml/library_wrappers/lib_tf_agents/py_bark_environment.py
bark_ml/library_wrappers/lib_tf_agents/networks/__init__.py
bark_ml/library_wrappers/lib_tf_agents/networks/gnn_actor_network.py
bark_ml/library_wrappers/lib_tf_agents/networks/gnn_critic_network.py
bark_ml/library_wrappers/lib_tf_agents/networks/gnn_actor_distribution_network.py
bark_ml/library_wrappers/lib_tf_agents/networks/gnn_value_network.py
bark_ml/library_wrappers/lib_tf_agents/networks/gnns/__init__.py
bark_ml/library_wrappers/lib_tf_agents/networks/gnns/graph_network.py
bark_ml/library_wrappers/lib_tf_agents/networks/gnns/interaction_wrapper.py
bark_ml/library_wrappers/lib_tf_agents/runners/__init__.py
bark_ml/library_wrappers/lib_tf_agents/runners/ppo_runner.py
bark_ml/library_wrappers/lib_tf_agents/runners/tfa_runner.py
bark_ml/library_wrappers/lib_tf_agents/runners/sac_runner.py
bark_ml/library_wrappers/lib_tf_agents/agents/__init__.py
bark_ml/library_wrappers/lib_tf_agents/agents/ppo_agent.py
