Metadata-Version: 2.1
Name: bark-ml
Version: 0.4.32
Summary: Gym Environments and Agents for Autonomous Driving
Home-page: https://github.com/bark-simulator/bark-ml
Author: Patrick Hart, Julian Bernhard, Klemens Esterle, Tobias Kessler
Author-email: patrickhart.1990@gmail.com
License: MIT
Keywords: gym environments,reinforcement learning,autonomous driving,machine learning
Platform: UNKNOWN
Classifier: Development Status :: 4 - Beta
Classifier: Intended Audience :: Science/Research
Classifier: License :: OSI Approved :: MIT License
Classifier: Operating System :: OS Independent
Classifier: Programming Language :: Python :: 3.7
Classifier: Programming Language :: Python :: 3.8
Requires-Python: >=3.7
Requires-Dist: pygame (>=1.9.6)
Requires-Dist: gym (>=0.17.2)
Requires-Dist: tensorflow (>=2.2.0)
Requires-Dist: tensorboard (>=2.2.2)
Requires-Dist: tf-agents (>=0.5.0)
Requires-Dist: tensorflow-probability (>=0.10.0)
Requires-Dist: bark-simulator (>=1.4.8)
Requires-Dist: graph-nets (>=1.1.0)
